spymot/__init__.py
spymot/_version.py
spymot/cli.py
spymot/v1/__init__.py
spymot/v1/cli.py
spymot/v2/__init__.py
spymot/v2/scripts/__init__.py
spymot/v2/scripts/enhanced_cli.py
spymot/v2/scripts/enhanced_demo.py
spymot/v2/scripts/interactive_cli.py
spymot-2.1.4.dev0.dist-info/licenses/LICENSE
spymot-2.1.4.dev0.dist-info/METADATA
spymot-2.1.4.dev0.dist-info/WHEEL
spymot-2.1.4.dev0.dist-info/entry_points.txt
spymot-2.1.4.dev0.dist-info/top_level.txt
spymot-2.1.4.dev0.dist-info/RECORD
