Metadata-Version: 2.4
Name: spymot
Version: 2.1.4.dev0
Summary: Advanced Protein Motif Detection with AlphaFold Structural Validation
Author-email: Erfan Zohrabi <erfanzohrabi.ez@gmail.com>
Maintainer-email: Erfan Zohrabi <erfanzohrabi.ez@gmail.com>
Project-URL: Homepage, https://github.com/ErfanZohrabi/Spymot
Project-URL: Documentation, https://github.com/ErfanZohrabi/Spymot/tree/main/documentation
Project-URL: Repository, https://github.com/ErfanZohrabi/Spymot.git
Project-URL: Bug Tracker, https://github.com/ErfanZohrabi/Spymot/issues
Project-URL: Changelog, https://github.com/ErfanZohrabi/Spymot/blob/main/CHANGELOG.md
Keywords: bioinformatics,protein,motif,alphafold,cancer,slims,signal-peptides,protein-structure,drug-discovery,structural-biology,computational-biology
Classifier: Development Status :: 4 - Beta
Classifier: Intended Audience :: Science/Research
Classifier: License :: OSI Approved :: MIT License
Classifier: Operating System :: OS Independent
Classifier: Programming Language :: Python :: 3
Classifier: Programming Language :: Python :: 3.8
Classifier: Programming Language :: Python :: 3.9
Classifier: Programming Language :: Python :: 3.10
Classifier: Programming Language :: Python :: 3.11
Classifier: Programming Language :: Python :: 3.12
Classifier: Topic :: Scientific/Engineering :: Bio-Informatics
Classifier: Topic :: Scientific/Engineering :: Medical Science Apps.
Classifier: Topic :: Scientific/Engineering :: Chemistry
Requires-Python: >=3.8
License-File: LICENSE
Requires-Dist: numpy>=1.19.0
Requires-Dist: requests>=2.25.0
Requires-Dist: click>=8.0.0
Requires-Dist: PyYAML>=5.4.0
Requires-Dist: biopython>=1.79
Requires-Dist: pandas>=1.3.0
Requires-Dist: tqdm>=4.60.0
Provides-Extra: dev
Requires-Dist: pytest>=6.0; extra == "dev"
Requires-Dist: pytest-cov; extra == "dev"
Requires-Dist: black; extra == "dev"
Requires-Dist: flake8; extra == "dev"
Requires-Dist: mypy; extra == "dev"
Requires-Dist: ruff; extra == "dev"
Provides-Extra: docs
Requires-Dist: sphinx; extra == "docs"
Requires-Dist: sphinx-rtd-theme; extra == "docs"
Requires-Dist: myst-parser; extra == "docs"
Provides-Extra: full
Requires-Dist: scipy>=1.7.0; extra == "full"
Requires-Dist: pandas>=1.3.0; extra == "full"
Requires-Dist: matplotlib>=3.5.0; extra == "full"
Requires-Dist: seaborn>=0.11.0; extra == "full"
Dynamic: license-file
